coinbase_agentkit/__init__.py
coinbase_agentkit/__version__.py
coinbase_agentkit/agentkit.py
coinbase_agentkit/network.py
coinbase_agentkit/action_providers/__init__.py
coinbase_agentkit/action_providers/action_decorator.py
coinbase_agentkit/action_providers/action_provider.py
coinbase_agentkit/action_providers/basename/README.md
coinbase_agentkit/action_providers/basename/__init__.py
coinbase_agentkit/action_providers/basename/basename_action_provider.py
coinbase_agentkit/action_providers/basename/constants.py
coinbase_agentkit/action_providers/basename/schemas.py
coinbase_agentkit/action_providers/cdp/README.md
coinbase_agentkit/action_providers/cdp/__init__.py
coinbase_agentkit/action_providers/cdp/cdp_api_action_provider.py
coinbase_agentkit/action_providers/cdp/cdp_evm_wallet_action_provider.py
coinbase_agentkit/action_providers/cdp/cdp_smart_wallet_action_provider.py
coinbase_agentkit/action_providers/cdp/schemas.py
coinbase_agentkit/action_providers/cdp/swap_utils.py
coinbase_agentkit/action_providers/compound/README.md
coinbase_agentkit/action_providers/compound/__init__.py
coinbase_agentkit/action_providers/compound/compound_action_provider.py
coinbase_agentkit/action_providers/compound/constants.py
coinbase_agentkit/action_providers/compound/schemas.py
coinbase_agentkit/action_providers/compound/utils.py
coinbase_agentkit/action_providers/erc20/README.md
coinbase_agentkit/action_providers/erc20/__init__.py
coinbase_agentkit/action_providers/erc20/constants.py
coinbase_agentkit/action_providers/erc20/erc20_action_provider.py
coinbase_agentkit/action_providers/erc20/schemas.py
coinbase_agentkit/action_providers/erc20/validators.py
coinbase_agentkit/action_providers/erc721/README.md
coinbase_agentkit/action_providers/erc721/__init__.py
coinbase_agentkit/action_providers/erc721/constants.py
coinbase_agentkit/action_providers/erc721/erc721_action_provider.py
coinbase_agentkit/action_providers/erc721/schemas.py
coinbase_agentkit-0.7.3.dist-info/METADATA
coinbase_agentkit-0.7.3.dist-info/WHEEL
coinbase_agentkit-0.7.3.dist-info/entry_points.txt
coinbase_agentkit-0.7.3.dist-info/RECORD
