Metadata-Version: 2.4
Name: coinbase-agentkit
Version: 0.7.3
Summary: Coinbase AgentKit
Author-email: John Peterson <john.peterson@coinbase.com>
License-Expression: Apache-2.0
Keywords: agent,agentkit,ai,cdp,coinbase,crypto,sdk
Requires-Python: ~=3.10
Requires-Dist: cdp-sdk<2,>=1.31.1
Requires-Dist: ecdsa<0.20,>=0.19.0
Requires-Dist: jsonschema<5,>=4.23.0
Requires-Dist: nilql<0.0.1,>=0.0.0a12
Requires-Dist: paramiko<4,>=3.5.1
Requires-Dist: pydantic~=2.0
Requires-Dist: pyjwt[crypto]<3,>=2.10.1
Requires-Dist: python-dotenv<2,>=1.0.1
Requires-Dist: requests<3,>=2.31.0
Requires-Dist: solana>=0.36.6
Requires-Dist: solders>=0.26.0
Requires-Dist: web3<8,>=7.6.0
Requires-Dist: x402<2,>=0.1.4
